large_excel_convert/__init__.py
large_excel_convert/bin.py
large_excel_convert/core.py
large_excel_convert/main.py
large_excel_convert/version.json
large_excel_convert-1.0.3.dist-info/METADATA
large_excel_convert-1.0.3.dist-info/WHEEL
large_excel_convert-1.0.3.dist-info/entry_points.txt
large_excel_convert-1.0.3.dist-info/top_level.txt
large_excel_convert-1.0.3.dist-info/RECORD
