Metadata-Version: 2.1
Name: large_excel_convert
Version: 1.0.3
Summary: Convert Large Excel File to CSV/TSV
Home-page: https://github.com/suqingdong/large_excel_convert
Author: suqingdong
Author-email: suqingdong1114@gmail.com
License: MIT License
Classifier: Development Status :: 5 - Production/Stable
Classifier: Operating System :: OS Independent
Classifier: Intended Audience :: Developers
Classifier: Programming Language :: Python
Classifier: Programming Language :: Python :: 3
Classifier: Programming Language :: Python :: 3.9
Classifier: Programming Language :: Python :: 3.10
Classifier: Programming Language :: Python :: 3.11
Classifier: Programming Language :: Python :: 3.12
Classifier: Topic :: Software Development :: Libraries
Requires-Dist: lxml
Requires-Dist: click
Requires-Dist: loguru
Requires-Dist: humanfriendly
